MANIFEST.in
README.md
setup.cfg
setup.py
docs/CHANGES.rst
docs/CONTRIBUTORS.rst
docs/EXAMPLES.rst
docs/HISTORY.rst
docs/REFERENCES.rst
src/incolumepy/__init__.py
src/incolumepy.saj_projects.egg-info/PKG-INFO
src/incolumepy.saj_projects.egg-info/not-zip-safe
src/incolumepy/saj_projects/clean.py
src/incolumepy/saj_projects/fs_report.py
src/incolumepy/saj_projects/legis.py
src/incolumepy/saj_projects/version.txt
src/incolumepy/saj_projects/config/__init__.py
src/incolumepy/saj_projects/config/config.yml
src/incolumepy/saj_projects/config/logger.yml
src/incolumepy/saj_projects/data/base_chefe_governo.csv
src/incolumepy/saj_projects/data/base_ministros.csv
src/incolumepy/saj_projects/data/base_presidente_exercicio.csv
src/incolumepy/saj_projects/data/base_vice.csv
src/incolumepy/saj_projects/data/presidentes.json
src/incolumepy/saj_projects/data/referendas.csv
src/incolumepy/saj_projects/drivers/chromedriver
src/incolumepy/saj_projects/drivers/chromedriver_linux64.zip
src/incolumepy/saj_projects/drivers/geckodriver
src/incolumepy/saj_projects/drivers/geckodriver-v0.23.0-linux64.tar.gz