Metadata-Version: 1.1
Name: incolumepy.saj-projects
Version: 20181226
Summary: package incolumepy incolumepy.saj_projects
Home-page: https://gitlab.com/development-incolume/saj_projects/
Author: @britodfbr
Author-email: contato@incolume.com.br
License: BSD
Project-URL: Documentation, https://gitlab.com/development-incolume/saj_projects/
Project-URL: Funding, None
Project-URL: Say Thanks!, None
Project-URL: Source, https://gitlab.com/development-incolume/saj_projects
Project-URL: Git, https://gitlab.com/development-incolume/saj_projects.git
Project-URL: Tracker, https://gitlab.com/development-incolume/saj_projects/issues
Project-URL: Oficial, 
Keywords: python incolumepy incolumepy.saj_projects
Platform: UNKNOWN
Classifier: Development Status :: 4 - Beta
Classifier: Operating System :: OS Independent
Classifier: Natural Language :: Portuguese (Brazilian)
Classifier: Programming Language :: Python
Classifier: Topic :: Software Development :: Libraries :: Python Modules
Classifier: Topic :: Utilities
